{
 "generated": "04 Jul 2026, 04:22 PM AEST",
 "total_contacts_now": 9870,
 "funnel_snapshot": [
  {
   "stage": "Brochure Download",
   "by_state": {
    "VIC": 0,
    "NSW": 1175,
    "QLD": 924,
    "SA": 0,
    "WA": 0,
    "NZ": 0
   },
   "total": 2099
  },
  {
   "stage": "New / To Contact",
   "by_state": {
    "VIC": 2,
    "NSW": 43,
    "QLD": 167,
    "SA": 0,
    "WA": 0,
    "NZ": 0
   },
   "total": 212
  },
  {
   "stage": "In Conversation",
   "by_state": {
    "VIC": 30,
    "NSW": 208,
    "QLD": 305,
    "SA": 17,
    "WA": 25,
    "NZ": 28
   },
   "total": 613
  },
  {
   "stage": "Quote Sent",
   "by_state": {
    "VIC": 9,
    "NSW": 24,
    "QLD": 13,
    "SA": 1,
    "WA": 3,
    "NZ": 0
   },
   "total": 50
  },
  {
   "stage": "Pending Decision",
   "by_state": {
    "VIC": 6,
    "NSW": 0,
    "QLD": 2,
    "SA": 2,
    "WA": 2,
    "NZ": 0
   },
   "total": 12
  },
  {
   "stage": "Deposit Received",
   "by_state": {
    "VIC": 0,
    "NSW": 3,
    "QLD": 2,
    "SA": 0,
    "WA": 3,
    "NZ": 0
   },
   "total": 8
  },
  {
   "stage": "Plans & Specs",
   "by_state": {
    "VIC": 4,
    "NSW": 0,
    "QLD": 0,
    "SA": 3,
    "WA": 2,
    "NZ": 0
   },
   "total": 9
  },
  {
   "stage": "Order Finalised",
   "by_state": {
    "VIC": 12,
    "NSW": 1,
    "QLD": 1,
    "SA": 1,
    "WA": 6,
    "NZ": 0
   },
   "total": 21
  },
  {
   "stage": "In Production",
   "by_state": {
    "VIC": 3,
    "NSW": 0,
    "QLD": 1,
    "SA": 0,
    "WA": 1,
    "NZ": 0
   },
   "total": 5
  },
  {
   "stage": "Handover Booked / Ready",
   "by_state": {
    "VIC": 5,
    "NSW": 0,
    "QLD": 1,
    "SA": 0,
    "WA": 1,
    "NZ": 0
   },
   "total": 7
  },
  {
   "stage": "Handover Complete",
   "by_state": {
    "VIC": 98,
    "NSW": 3,
    "QLD": 20,
    "SA": 6,
    "WA": 4,
    "NZ": 0
   },
   "total": 131
  }
 ],
 "funnel_states": [
  "VIC",
  "NSW",
  "QLD",
  "SA",
  "WA",
  "NZ"
 ],
 "delivery_board": [
  {
   "stage": "Deposit Received",
   "count": 2,
   "items": [
    {
     "chassis": "WL1270",
     "name": "Solara Brochure Lead",
     "state": "NSW"
    },
    {
     "chassis": "WL969",
     "name": "",
     "state": "WA"
    }
   ]
  },
  {
   "stage": "Plans & Specs",
   "count": 6,
   "items": [
    {
     "chassis": "WL1282",
     "name": "DUNN XT2100K-F2",
     "state": "SA"
    },
    {
     "chassis": "WL1284",
     "name": "",
     "state": "VIC"
    },
    {
     "chassis": "WL1309",
     "name": "Murfet AM1709R_L",
     "state": "VIC"
    },
    {
     "chassis": "WL1317",
     "name": "XTR- Andreas Sonder",
     "state": "WA"
    },
    {
     "chassis": "WL1321",
     "name": "SQUIRE SO22 R C",
     "state": "SA"
    },
    {
     "chassis": "WL1345",
     "name": "kim & andrea",
     "state": "WA"
    }
   ]
  },
  {
   "stage": "Order Finalised",
   "count": 16,
   "items": [
    {
     "chassis": "WL1088",
     "name": "Boulton HO2206F-B4",
     "state": "VIC"
    },
    {
     "chassis": "WL1234",
     "name": "XT2311K1-F4.3 HADLEY",
     "state": "WA"
    },
    {
     "chassis": "WL1259",
     "name": "Healy XT1906QRC",
     "state": "VIC"
    },
    {
     "chassis": "WL1264",
     "name": "Solara Brochure Lead",
     "state": "NSW"
    },
    {
     "chassis": "WL1268",
     "name": "Minogue",
     "state": "VIC"
    },
    {
     "chassis": "WL1278",
     "name": "SO1806ML Aiden Brock",
     "state": "VIC"
    },
    {
     "chassis": "WL1285",
     "name": "Darling XT2106",
     "state": "VIC"
    },
    {
     "chassis": "WL1292",
     "name": "Murray AM2100Q-F2.0",
     "state": "SA"
    },
    {
     "chassis": "WL1303",
     "name": "HO2106EW",
     "state": "VIC"
    },
    {
     "chassis": "WL1310",
     "name": "Shell HO2106Q-M-SC C",
     "state": "VIC"
    },
    {
     "chassis": "WL1316",
     "name": "HURLEY",
     "state": "WA"
    },
    {
     "chassis": "WL1318",
     "name": "XT1906RL Peter & Don",
     "state": "WA"
    },
    {
     "chassis": "WL1335",
     "name": "BURKE",
     "state": "VIC"
    },
    {
     "chassis": "WL1343",
     "name": "SCRIVEN AM1806",
     "state": "WA"
    },
    {
     "chassis": "WL1357",
     "name": "BIFFIN",
     "state": "WA"
    },
    {
     "chassis": "WL1358",
     "name": "Dyson",
     "state": "WA"
    }
   ]
  },
  {
   "stage": "In Production",
   "count": 5,
   "items": [
    {
     "chassis": "WL1177",
     "name": "ZILLWOOD",
     "state": "VIC"
    },
    {
     "chassis": "WL1258",
     "name": "Nick Barnett",
     "state": "WA"
    },
    {
     "chassis": "WL1265",
     "name": "Carpenter",
     "state": "QLD"
    },
    {
     "chassis": "WL1273",
     "name": "CROXFORD AM21000M_L_",
     "state": "VIC"
    },
    {
     "chassis": "WL1288",
     "name": "JOWETT HO2100-M-XLE",
     "state": "VIC"
    }
   ]
  },
  {
   "stage": "Ready / Handover Booked",
   "count": 6,
   "items": [
    {
     "chassis": "WL1154",
     "name": "",
     "state": "WA"
    },
    {
     "chassis": "WL1248",
     "name": "DINGLEY XT1906",
     "state": "VIC"
    },
    {
     "chassis": "WL1253",
     "name": "KAESTNER HO2311Q-F2.",
     "state": "VIC"
    },
    {
     "chassis": "WL1289",
     "name": "XTR 2206 F3.3",
     "state": "VIC"
    },
    {
     "chassis": "WL1290",
     "name": "\u00a0Andrew & Karen Simp",
     "state": "VIC"
    },
    {
     "chassis": "WL1332",
     "name": "PAGE AM2107EW-F2.4",
     "state": "VIC"
    }
   ]
  }
 ],
 "configurator": {
  "sessions_alltime": 5514,
  "submitters_alltime": 1826,
  "by_state": {
   "VIC": 446,
   "NSW": 383,
   "QLD": 83,
   "WA": 61,
   "SA": 22,
   "TAS": 15,
   "NT": 2,
   "NZ": 1,
   "No state recorded": 813
  },
  "conversion": {
   "In conversation": 90,
   "Back to market": 62,
   "Quote sent": 6,
   "Deposit+ (committed)": 2,
   "Won / Sold": 1,
   "New / other": 1
  }
 },
 "months": [
  {
   "key": "2026-01",
   "label": "January 2026",
   "partial": false,
   "ac": {
    "new_contacts": 322,
    "ad_enquiries": 0,
    "deals_created": 317,
    "deals_by_type": {
     "Brochure downloads": 177,
     "Configurator": 79,
     "Sales-entered / other": 51,
     "Shows & events": 9,
     "Virtual consults": 1
    },
    "deals_by_state": {
     "VIC": 82,
     "WA": 49,
     "QLD": 71,
     "SA": 17,
     "NSW": 92,
     "NZ": 6
    },
    "leads_by_state": {
     "VIC": 82,
     "WA": 49,
     "QLD": 71,
     "SA": 17,
     "NSW": 92,
     "NZ": 6
    },
    "contacts_by_state": {
     "NSW": 90,
     "VIC": 73,
     "QLD": 71,
     "WA": 44,
     "SA": 17,
     "TAS": 7,
     "NZ": 6,
     "NT": 2,
     "No state recorded": 12
    },
    "brochures_by_model": {
     "XTR": 92,
     "Solara": 83,
     "Amaroo": 82,
     "Hornet": 39,
     "COTY": 13
    },
    "configurator_leads": 77,
    "deposits_flow": {
     "VIC": 1
    },
    "handovers_flow": {
     "VIC": 12
    },
    "deposits_names": [
     "WL1169 Rossetto"
    ],
    "handovers_names": [
     "WL1122 Biggs",
     "WL1045 KEOGH",
     "WL1120 COOK AM2300Q2-F2.4",
     "WL1121 Higginbottom AM2107F",
     "WL1117 Wilson AM2206EW-F2.4",
     "WL1116 ALLMAN",
     "WL1112 MARTH",
     "WL1101 LACEY",
     "WL1137 ANDREWS",
     "WL1156 LEMON HO2100K-F2.0"
    ],
    "emails": {
     "broadcast_count": 1,
     "sent": 1600,
     "avg_open_pct": 47.7,
     "avg_click_pct": 15.0,
     "automated_sends": 0,
     "broadcasts": [
      {
       "name": "January Newsletter 2026",
       "sends": 1600,
       "opens": 763,
       "clicks": 240,
       "date": "2026-01-29"
      }
     ]
    }
   },
   "wl": null,
   "ob": null,
   "social_note": "Social analytics tracking in Vista began April 2026, so earlier months show CRM only."
  },
  {
   "key": "2026-02",
   "label": "February 2026",
   "partial": false,
   "ac": {
    "new_contacts": 303,
    "ad_enquiries": 0,
    "deals_created": 335,
    "deals_by_type": {
     "Brochure downloads": 139,
     "Sales-entered / other": 113,
     "Configurator": 45,
     "Shows & events": 36,
     "Virtual consults": 2
    },
    "deals_by_state": {
     "SA": 33,
     "VIC": 148,
     "QLD": 47,
     "WA": 54,
     "NSW": 51,
     "NZ": 2
    },
    "leads_by_state": {
     "SA": 33,
     "VIC": 148,
     "QLD": 47,
     "WA": 54,
     "NSW": 51,
     "NZ": 2
    },
    "contacts_by_state": {
     "VIC": 105,
     "NSW": 54,
     "QLD": 51,
     "WA": 47,
     "SA": 26,
     "TAS": 4,
     "NT": 3,
     "NZ": 2,
     "No state recorded": 11
    },
    "brochures_by_model": {
     "Solara": 89,
     "XTR": 70,
     "Amaroo": 57,
     "Hornet": 33,
     "COTY": 11
    },
    "configurator_leads": 45,
    "deposits_flow": {},
    "handovers_flow": {
     "VIC": 1
    },
    "deposits_names": [],
    "handovers_names": [
     "WL1148 Davey HO2200RCA"
    ],
    "emails": {
     "broadcast_count": 5,
     "sent": 4002,
     "avg_open_pct": 44.9,
     "avg_click_pct": 7.3,
     "automated_sends": 0,
     "broadcasts": [
      {
       "name": "February Newsletter 2026 ",
       "sends": 1608,
       "opens": 814,
       "clicks": 145,
       "date": "2026-02-26"
      },
      {
       "name": "Victorian Caravan & Camping Supershow",
       "sends": 748,
       "opens": 309,
       "clicks": 54,
       "date": "2026-02-12"
      },
      {
       "name": "Victorian Caravan & Camping Supershow - Reminder (FINAL)",
       "sends": 672,
       "opens": 231,
       "clicks": 15,
       "date": "2026-02-16"
      },
      {
       "name": "Victorian Caravan & Camping Supershow - Final",
       "sends": 616,
       "opens": 281,
       "clicks": 56,
       "date": "2026-02-12"
      },
      {
       "name": "Come join our NSW Open Day\u202f\u2728 ",
       "sends": 358,
       "opens": 160,
       "clicks": 22,
       "date": "2026-02-05"
      }
     ]
    }
   },
   "wl": null,
   "ob": null,
   "social_note": "Social analytics tracking in Vista began April 2026, so earlier months show CRM only."
  },
  {
   "key": "2026-03",
   "label": "March 2026",
   "partial": false,
   "ac": {
    "new_contacts": 195,
    "ad_enquiries": 0,
    "deals_created": 177,
    "deals_by_type": {
     "Brochure downloads": 95,
     "Sales-entered / other": 41,
     "Configurator": 31,
     "Shows & events": 8,
     "Virtual consults": 2
    },
    "deals_by_state": {
     "NSW": 32,
     "VIC": 50,
     "WA": 49,
     "QLD": 28,
     "SA": 14,
     "NZ": 4
    },
    "leads_by_state": {
     "NSW": 32,
     "VIC": 50,
     "WA": 49,
     "QLD": 28,
     "SA": 14,
     "NZ": 4
    },
    "contacts_by_state": {
     "WA": 50,
     "VIC": 42,
     "NSW": 30,
     "QLD": 29,
     "SA": 14,
     "NZ": 4,
     "TAS": 3,
     "No state recorded": 23
    },
    "brochures_by_model": {
     "Solara": 50,
     "XTR": 38,
     "Amaroo": 37,
     "Hornet": 26,
     "COTY": 3
    },
    "configurator_leads": 29,
    "deposits_flow": {},
    "handovers_flow": {
     "VIC": 4,
     "WA": 1
    },
    "deposits_names": [],
    "handovers_names": [
     "WL1242 XTR",
     "WL1183 Fletcher AM1709RL",
     "WL1129 CARNEY HO2100F-B2",
     "WL1182 Ben Fuller AM2106EW-",
     "WL1230 Brad Glew HO1906R"
    ],
    "emails": {
     "broadcast_count": 5,
     "sent": 3110,
     "avg_open_pct": 39.1,
     "avg_click_pct": 7.2,
     "automated_sends": 0,
     "broadcasts": [
      {
       "name": "March Newsletter 2026  ",
       "sends": 1667,
       "opens": 737,
       "clicks": 162,
       "date": "2026-03-30"
      },
      {
       "name": "VIC - Border Show 2026",
       "sends": 698,
       "opens": 294,
       "clicks": 32,
       "date": "2026-03-24"
      },
      {
       "name": "VIC - Border Show 2026",
       "sends": 431,
       "opens": 69,
       "clicks": 3,
       "date": "2026-03-26"
      },
      {
       "name": "WA - Perth Caravan and Camping Show 2026",
       "sends": 205,
       "opens": 98,
       "clicks": 24,
       "date": "2026-03-16"
      },
      {
       "name": "WA - Perth Caravan and Camping Show 2026",
       "sends": 109,
       "opens": 18,
       "clicks": 2,
       "date": "2026-03-18"
      }
     ]
    }
   },
   "wl": null,
   "ob": null,
   "social_note": "Social analytics tracking in Vista began April 2026, so earlier months show CRM only."
  },
  {
   "key": "2026-04",
   "label": "April 2026",
   "partial": false,
   "ac": {
    "new_contacts": 537,
    "ad_enquiries": 0,
    "deals_created": 232,
    "deals_by_type": {
     "Brochure downloads": 94,
     "Configurator": 48,
     "Shows & events": 44,
     "Sales-entered / other": 43,
     "Virtual consults": 3
    },
    "deals_by_state": {
     "NSW": 95,
     "VIC": 55,
     "QLD": 48,
     "WA": 17,
     "SA": 14,
     "NZ": 3
    },
    "leads_by_state": {
     "NSW": 95,
     "VIC": 55,
     "QLD": 48,
     "WA": 17,
     "SA": 14,
     "NZ": 3
    },
    "contacts_by_state": {
     "VIC": 154,
     "NSW": 127,
     "QLD": 67,
     "WA": 31,
     "SA": 24,
     "TAS": 9,
     "NT": 4,
     "NZ": 3,
     "No state recorded": 118
    },
    "brochures_by_model": {
     "XTR": 44,
     "Solara": 43,
     "Amaroo": 35,
     "Hornet": 8,
     "COTY": 2
    },
    "configurator_leads": 47,
    "deposits_flow": {},
    "handovers_flow": {
     "WA": 1,
     "VIC": 18,
     "SA": 2
    },
    "deposits_names": [],
    "handovers_names": [
     "WL1189 Ryan Wilkie",
     "WL1019 Mike Millott",
     "WL1115 Agrifridge Pty Ltd",
     "WL1187 AM2211 KEENAN",
     "WL1136 HO2200Q-RC- ANDY",
     "WL1138 McDowell",
     "WL1162 AM1906 Culph",
     "WL1164 Jenna Spurling",
     "WL934 ",
     "WL1160 4X4 Brothers"
    ],
    "emails": {
     "broadcast_count": 5,
     "sent": 3064,
     "avg_open_pct": 41.6,
     "avg_click_pct": 13.6,
     "automated_sends": 0,
     "broadcasts": [
      {
       "name": "April Newsletter 2026 ",
       "sends": 1793,
       "opens": 821,
       "clicks": 358,
       "date": "2026-04-29"
      },
      {
       "name": "NSW - Rosehill Show",
       "sends": 374,
       "opens": 156,
       "clicks": 30,
       "date": "2026-04-21"
      },
      {
       "name": "NSW Open Day",
       "sends": 367,
       "opens": 144,
       "clicks": 18,
       "date": "2026-04-17"
      },
      {
       "name": "QLD - Nambour Show",
       "sends": 312,
       "opens": 118,
       "clicks": 8,
       "date": "2026-04-15"
      },
      {
       "name": "NSW - Rosehill Show",
       "sends": 218,
       "opens": 37,
       "clicks": 3,
       "date": "2026-04-27"
      }
     ]
    }
   },
   "wl": {
    "channels": {
     "youtube": {
      "followers": 681,
      "follower_change": 5,
      "impressions": 3626,
      "engagement": 30,
      "likes": 18,
      "comments": 0,
      "shares": 12,
      "profile_views": 0,
      "saves": 0,
      "messages": 0
     },
     "linkedin": {
      "followers": 154,
      "follower_change": 4,
      "impressions": 44,
      "engagement": 2,
      "likes": 0,
      "comments": 0,
      "shares": 0,
      "profile_views": 0,
      "saves": 0,
      "messages": 0
     },
     "tiktok": {
      "followers": 445,
      "follower_change": 2,
      "impressions": 2301,
      "engagement": 32,
      "likes": 29,
      "comments": 2,
      "shares": 1,
      "profile_views": 0,
      "saves": 0,
      "messages": 0
     },
     "facebook": {
      "followers": 24417,
      "follower_change": 62,
      "impressions": 682131,
      "engagement": 467,
      "likes": 466,
      "comments": 1,
      "shares": 0,
      "profile_views": 0,
      "saves": 0,
      "messages": 0
     },
     "instagram": {
      "followers": 8429,
      "follower_change": 66,
      "impressions": 111639,
      "engagement": 1387,
      "likes": 965,
      "comments": 53,
      "shares": 132,
      "profile_views": 1010,
      "saves": 0,
      "messages": 0
     },
     "pinterest": {
      "followers": 18,
      "follower_change": 1,
      "impressions": 22292,
      "engagement": 1096,
      "likes": 0,
      "comments": 0,
      "shares": 0,
      "profile_views": 0,
      "saves": 0,
      "messages": 0
     }
    },
    "totals": {
     "followers": 34144,
     "follower_change": 140,
     "impressions": 822033,
     "engagement": 3014,
     "likes": 1478,
     "comments": 56,
     "shares": 145,
     "profile_views": 1010,
     "saves": 0,
     "messages": 0,
     "engagement_rate": 0.37
    },
    "daily": {
     "dates": [
      "04/01",
      "04/02",
      "04/03",
      "04/04",
      "04/05",
      "04/06",
      "04/07",
      "04/08",
      "04/09",
      "04/10",
      "04/11",
      "04/12",
      "04/13",
      "04/14",
      "04/15",
      "04/16",
      "04/17",
      "04/18",
      "04/19",
      "04/20",
      "04/21",
      "04/22",
      "04/23",
      "04/24",
      "04/25",
      "04/26",
      "04/27",
      "04/28",
      "04/29",
      "04/30"
     ],
     "impressions": [
      24531,
      16848,
      23024,
      27522,
      32093,
      28916,
      27996,
      25798,
      26494,
      38657,
      17769,
      24627,
      25233,
      25498,
      21947,
      22082,
      25727,
      26644,
      27715,
      26926,
      25301,
      27322,
      27782,
      47108,
      38306,
      31205,
      32436,
      27542,
      23239,
      25745
     ],
     "engagement": [
      57,
      94,
      88,
      69,
      67,
      89,
      84,
      99,
      142,
      109,
      68,
      58,
      128,
      86,
      66,
      101,
      107,
      119,
      90,
      72,
      106,
      95,
      93,
      64,
      64,
      59,
      285,
      147,
      142,
      166
     ]
    }
   },
   "ob": {
    "channels": {
     "facebook": {
      "followers": 1121,
      "follower_change": 9,
      "impressions": 342359,
      "engagement": 99,
      "likes": 97,
      "comments": 2,
      "shares": 0,
      "profile_views": 0,
      "saves": 0,
      "messages": 0
     },
     "instagram": {
      "followers": 619,
      "follower_change": 3,
      "impressions": 25997,
      "engagement": 269,
      "likes": 214,
      "comments": 6,
      "shares": 15,
      "profile_views": 69,
      "saves": 0,
      "messages": 0
     }
    },
    "totals": {
     "followers": 1740,
     "follower_change": 12,
     "impressions": 368356,
     "engagement": 368,
     "likes": 311,
     "comments": 8,
     "shares": 15,
     "profile_views": 69,
     "saves": 0,
     "messages": 0,
     "engagement_rate": 0.1
    },
    "daily": {
     "dates": [
      "04/01",
      "04/02",
      "04/03",
      "04/04",
      "04/05",
      "04/06",
      "04/07",
      "04/08",
      "04/09",
      "04/10",
      "04/11",
      "04/12",
      "04/13",
      "04/14",
      "04/15",
      "04/16",
      "04/17",
      "04/18",
      "04/19",
      "04/20",
      "04/21",
      "04/22",
      "04/23",
      "04/24",
      "04/25",
      "04/26",
      "04/27",
      "04/28",
      "04/29",
      "04/30"
     ],
     "impressions": [
      13963,
      13258,
      13502,
      11119,
      11905,
      12228,
      11559,
      10415,
      15220,
      10229,
      13925,
      12685,
      11736,
      11498,
      10244,
      12525,
      12353,
      13592,
      13661,
      12383,
      13873,
      13507,
      10991,
      10968,
      10491,
      15262,
      11178,
      9677,
      11288,
      13121
     ],
     "engagement": [
      21,
      48,
      19,
      7,
      5,
      18,
      17,
      6,
      8,
      3,
      13,
      5,
      9,
      17,
      5,
      9,
      5,
      6,
      3,
      1,
      4,
      13,
      12,
      8,
      20,
      40,
      5,
      6,
      9,
      26
     ]
    }
   }
  },
  {
   "key": "2026-05",
   "label": "May 2026",
   "partial": false,
   "ac": {
    "new_contacts": 236,
    "ad_enquiries": 0,
    "deals_created": 215,
    "deals_by_type": {
     "Brochure downloads": 79,
     "Shows & events": 59,
     "Configurator": 43,
     "Sales-entered / other": 30,
     "Virtual consults": 4
    },
    "deals_by_state": {
     "NSW": 95,
     "VIC": 39,
     "SA": 13,
     "QLD": 46,
     "WA": 22
    },
    "leads_by_state": {
     "NSW": 95,
     "VIC": 39,
     "SA": 13,
     "QLD": 46,
     "WA": 22
    },
    "contacts_by_state": {
     "NSW": 94,
     "QLD": 52,
     "VIC": 34,
     "WA": 25,
     "SA": 13,
     "TAS": 5,
     "NT": 1,
     "No state recorded": 12
    },
    "brochures_by_model": {
     "XTR": 34,
     "Solara": 31,
     "Amaroo": 24,
     "Hornet": 11,
     "COTY": 2
    },
    "configurator_leads": 42,
    "deposits_flow": {
     "NSW": 1
    },
    "handovers_flow": {
     "VIC": 6,
     "NSW": 2
    },
    "deposits_names": [
     "WL1270 Solara Brochure Lead"
    ],
    "handovers_names": [
     "WL1186 AM2106",
     "WL1206 HO2206EW-F4.3  Ana &",
     "WL1081 Foden",
     "WL1203 Polly & Chris Porter",
     "WL1170 XTR",
     "WL1217 DEIMEL",
     "WL1070 XTR Brochure Lead",
     "WL1236 Mansfield SO1806"
    ],
    "emails": {
     "broadcast_count": 4,
     "sent": 4552,
     "avg_open_pct": 37.6,
     "avg_click_pct": 10.0,
     "automated_sends": 0,
     "broadcasts": [
      {
       "name": "Demo 24/25 Plate Sale",
       "sends": 2496,
       "opens": 1213,
       "clicks": 368,
       "date": "2026-05-01"
      },
      {
       "name": "Demo 24/25 Plate Sale",
       "sends": 1336,
       "opens": 218,
       "clicks": 57,
       "date": "2026-05-05"
      },
      {
       "name": "VIC - Bendigo Show",
       "sends": 367,
       "opens": 149,
       "clicks": 16,
       "date": "2026-05-27"
      },
      {
       "name": "QLD - Mackay Outdoor Adventure plus Home & Lifestyle Expo!",
       "sends": 353,
       "opens": 131,
       "clicks": 12,
       "date": "2026-05-21"
      }
     ]
    }
   },
   "wl": {
    "channels": {
     "youtube": {
      "followers": 712,
      "follower_change": 29,
      "impressions": 13570,
      "engagement": 167,
      "likes": 124,
      "comments": 6,
      "shares": 25,
      "profile_views": 0,
      "saves": 0,
      "messages": 0
     },
     "linkedin": {
      "followers": 158,
      "follower_change": 4,
      "impressions": 149,
      "engagement": 15,
      "likes": 9,
      "comments": 0,
      "shares": 0,
      "profile_views": 0,
      "saves": 0,
      "messages": 0
     },
     "tiktok": {
      "followers": 471,
      "follower_change": 25,
      "impressions": 9427,
      "engagement": 221,
      "likes": 175,
      "comments": 11,
      "shares": 24,
      "profile_views": 0,
      "saves": 0,
      "messages": 0
     },
     "facebook": {
      "followers": 24441,
      "follower_change": 20,
      "impressions": 715342,
      "engagement": 503,
      "likes": 494,
      "comments": 7,
      "shares": 2,
      "profile_views": 0,
      "saves": 0,
      "messages": 20
     },
     "instagram": {
      "followers": 8631,
      "follower_change": 206,
      "impressions": 147178,
      "engagement": 1906,
      "likes": 1111,
      "comments": 113,
      "shares": 215,
      "profile_views": 1330,
      "saves": 112,
      "messages": 35
     },
     "pinterest": {
      "followers": 16,
      "follower_change": 0,
      "impressions": 18407,
      "engagement": 885,
      "likes": 0,
      "comments": 0,
      "shares": 0,
      "profile_views": 0,
      "saves": 0,
      "messages": 0
     }
    },
    "totals": {
     "followers": 34429,
     "follower_change": 284,
     "impressions": 904073,
     "engagement": 3697,
     "likes": 1913,
     "comments": 137,
     "shares": 266,
     "profile_views": 1330,
     "saves": 112,
     "messages": 55,
     "engagement_rate": 0.41
    },
    "daily": {
     "dates": [
      "05/01",
      "05/02",
      "05/03",
      "05/04",
      "05/05",
      "05/06",
      "05/07",
      "05/08",
      "05/09",
      "05/10",
      "05/11",
      "05/12",
      "05/13",
      "05/14",
      "05/15",
      "05/16",
      "05/17",
      "05/18",
      "05/19",
      "05/20",
      "05/21",
      "05/22",
      "05/23",
      "05/24",
      "05/25",
      "05/26",
      "05/27",
      "05/28",
      "05/29",
      "05/30"
     ],
     "impressions": [
      34124,
      31819,
      32621,
      32670,
      30867,
      29243,
      28697,
      32514,
      31369,
      32381,
      38776,
      32341,
      32248,
      33016,
      26278,
      35038,
      34398,
      28929,
      31054,
      26888,
      27223,
      28139,
      33773,
      29532,
      29973,
      23935,
      23225,
      23033,
      24360,
      25609
     ],
     "engagement": [
      189,
      137,
      131,
      99,
      151,
      76,
      104,
      144,
      78,
      103,
      192,
      163,
      88,
      129,
      115,
      183,
      145,
      70,
      90,
      90,
      123,
      129,
      257,
      106,
      132,
      73,
      114,
      90,
      91,
      105
     ]
    }
   },
   "ob": {
    "channels": {
     "facebook": {
      "followers": 1130,
      "follower_change": 8,
      "impressions": 389915,
      "engagement": 72,
      "likes": 70,
      "comments": 2,
      "shares": 0,
      "profile_views": 0,
      "saves": 0,
      "messages": 1
     },
     "instagram": {
      "followers": 684,
      "follower_change": 64,
      "impressions": 22552,
      "engagement": 402,
      "likes": 288,
      "comments": 16,
      "shares": 33,
      "profile_views": 86,
      "saves": 17,
      "messages": 3
     }
    },
    "totals": {
     "followers": 1814,
     "follower_change": 72,
     "impressions": 412467,
     "engagement": 474,
     "likes": 358,
     "comments": 18,
     "shares": 33,
     "profile_views": 86,
     "saves": 17,
     "messages": 4,
     "engagement_rate": 0.11
    },
    "daily": {
     "dates": [
      "05/01",
      "05/02",
      "05/03",
      "05/04",
      "05/05",
      "05/06",
      "05/07",
      "05/08",
      "05/09",
      "05/10",
      "05/11",
      "05/12",
      "05/13",
      "05/14",
      "05/15",
      "05/16",
      "05/17",
      "05/18",
      "05/19",
      "05/20",
      "05/21",
      "05/22",
      "05/23",
      "05/24",
      "05/25",
      "05/26",
      "05/27",
      "05/28",
      "05/29",
      "05/30"
     ],
     "impressions": [
      15649,
      14387,
      16869,
      12144,
      12958,
      14210,
      12760,
      12728,
      14099,
      13763,
      15487,
      13495,
      13081,
      14527,
      12514,
      15990,
      19023,
      14935,
      14455,
      14078,
      10678,
      12576,
      15042,
      17551,
      10785,
      14213,
      11433,
      12114,
      10399,
      10524
     ],
     "engagement": [
      12,
      16,
      5,
      7,
      16,
      18,
      6,
      10,
      1,
      5,
      6,
      4,
      9,
      34,
      13,
      28,
      14,
      11,
      16,
      26,
      7,
      11,
      19,
      8,
      49,
      17,
      42,
      26,
      13,
      25
     ]
    }
   }
  },
  {
   "key": "2026-06",
   "label": "June 2026",
   "partial": false,
   "ac": {
    "new_contacts": 227,
    "ad_enquiries": 40,
    "deals_created": 273,
    "deals_by_type": {
     "Brochure downloads": 72,
     "Campaign offers": 72,
     "Shows & events": 51,
     "Configurator": 45,
     "Sales-entered / other": 25,
     "Ad enquiries": 7,
     "Virtual consults": 1
    },
    "deals_by_state": {
     "QLD": 103,
     "NSW": 47,
     "VIC": 86,
     "WA": 31,
     "SA": 5,
     "NZ": 1
    },
    "leads_by_state": {
     "QLD": 103,
     "NSW": 47,
     "VIC": 86,
     "WA": 31,
     "SA": 5,
     "NZ": 1
    },
    "contacts_by_state": {
     "QLD": 95,
     "NSW": 44,
     "VIC": 31,
     "WA": 27,
     "TAS": 6,
     "SA": 5,
     "No state recorded": 19
    },
    "brochures_by_model": {
     "Solara": 47,
     "Amaroo": 33,
     "XTR": 31,
     "Hornet": 14
    },
    "configurator_leads": 41,
    "deposits_flow": {
     "WA": 2,
     "SA": 1
    },
    "handovers_flow": {
     "VIC": 8
    },
    "deposits_names": [
     "WL969 ",
     "WL1277 Miller AM2107EWF",
     "WL1320 Sutcliffe AM1709"
    ],
    "handovers_names": [
     "WL1035 ",
     "WL1196 LOVE AM2311Q-F4.3",
     "WL1243 Rennae & Mark Ruggie",
     "WL899 Della-Mina AM1709R_L",
     "WL1280 SANDY XTR",
     "WL1241 AM1709RL ROGERS",
     "WL1124 STROTHER AM1709RL",
     "WL1251 THYNE AM2107"
    ],
    "emails": {
     "broadcast_count": 5,
     "sent": 8729,
     "avg_open_pct": 44.8,
     "avg_click_pct": 6.5,
     "automated_sends": 2217,
     "broadcasts": [
      {
       "name": "June Newsletter",
       "sends": 2661,
       "opens": 1073,
       "clicks": 147,
       "date": "2026-06-26"
      },
      {
       "name": "EOFYS 2026 - Amaroo",
       "sends": 2619,
       "opens": 1108,
       "clicks": 128,
       "date": "2026-06-12"
      },
      {
       "name": "May Newsletter 2026 ",
       "sends": 2577,
       "opens": 1382,
       "clicks": 255,
       "date": "2026-06-02"
      },
      {
       "name": "QLD - Let's Go Queensland Caravan & Camping Supershow (Copy) (Copy)",
       "sends": 509,
       "opens": 204,
       "clicks": 20,
       "date": "2026-06-01"
      },
      {
       "name": "QLD - Let's Go Queensland Caravan & Camping Supershow",
       "sends": 363,
       "opens": 146,
       "clicks": 17,
       "date": "2026-06-01"
      }
     ]
    }
   },
   "wl": {
    "channels": {
     "youtube": {
      "followers": 737,
      "follower_change": 22,
      "impressions": 24154,
      "engagement": 165,
      "likes": 134,
      "comments": 3,
      "shares": 15,
      "profile_views": 0,
      "saves": 0,
      "messages": 0
     },
     "linkedin": {
      "followers": 164,
      "follower_change": 7,
      "impressions": 1071,
      "engagement": 151,
      "likes": 44,
      "comments": 4,
      "shares": 3,
      "profile_views": 0,
      "saves": 0,
      "messages": 0
     },
     "tiktok": {
      "followers": 506,
      "follower_change": 35,
      "impressions": 10502,
      "engagement": 282,
      "likes": 229,
      "comments": 6,
      "shares": 23,
      "profile_views": 0,
      "saves": 0,
      "messages": 0
     },
     "facebook": {
      "followers": 24460,
      "follower_change": 22,
      "impressions": 607840,
      "engagement": 420,
      "likes": 399,
      "comments": 16,
      "shares": 5,
      "profile_views": 0,
      "saves": 0,
      "messages": 29
     },
     "instagram": {
      "followers": 9131,
      "follower_change": 546,
      "impressions": 258175,
      "engagement": 5884,
      "likes": 3084,
      "comments": 209,
      "shares": 1034,
      "profile_views": 3333,
      "saves": 415,
      "messages": 54
     },
     "pinterest": {
      "followers": 18,
      "follower_change": 1,
      "impressions": 18821,
      "engagement": 1023,
      "likes": 0,
      "comments": 0,
      "shares": 0,
      "profile_views": 0,
      "saves": 0,
      "messages": 0
     }
    },
    "totals": {
     "followers": 35016,
     "follower_change": 633,
     "impressions": 920563,
     "engagement": 7925,
     "likes": 3890,
     "comments": 238,
     "shares": 1080,
     "profile_views": 3333,
     "saves": 415,
     "messages": 83,
     "engagement_rate": 0.86
    },
    "daily": {
     "dates": [
      "06/01",
      "06/02",
      "06/03",
      "06/04",
      "06/05",
      "06/06",
      "06/07",
      "06/08",
      "06/09",
      "06/10",
      "06/11",
      "06/12",
      "06/13",
      "06/14",
      "06/15",
      "06/16",
      "06/17",
      "06/18",
      "06/19",
      "06/20",
      "06/21",
      "06/22",
      "06/23",
      "06/24",
      "06/25",
      "06/26",
      "06/27",
      "06/28",
      "06/29",
      "06/30"
     ],
     "impressions": [
      27087,
      36175,
      34171,
      31265,
      24729,
      38336,
      31563,
      34133,
      28407,
      28197,
      26145,
      27959,
      27075,
      26061,
      24643,
      28698,
      27346,
      26646,
      26852,
      20006,
      20013,
      28686,
      28132,
      27534,
      21966,
      24813,
      38211,
      80228,
      34802,
      40684
     ],
     "engagement": [
      155,
      216,
      204,
      156,
      188,
      128,
      114,
      181,
      110,
      128,
      146,
      162,
      177,
      91,
      105,
      99,
      250,
      151,
      208,
      132,
      140,
      474,
      313,
      230,
      139,
      160,
      633,
      1637,
      597,
      501
     ]
    },
    "top_posts": [
     {
      "msg": "Three kids, three beds, zero compromises",
      "network": "instagram",
      "type": "Reel",
      "date": "27 Jun",
      "link": "https://www.instagram.com/reel/DaFOdETkwYy/",
      "impressions": 59446,
      "engagement": 1896,
      "likes": 930,
      "shares": 689,
      "saves": 244
     },
     {
      "msg": "The real test of a family van",
      "network": "instagram",
      "type": "Reel",
      "date": "17 Jun",
      "link": "https://www.instagram.com/reel/DZrd4y7gXqM/",
      "impressions": 55476,
      "engagement": 1568,
      "likes": 637,
      "shares": 726,
      "saves": 193
     },
     {
      "msg": "Just the two of you, and the open road",
      "network": "instagram",
      "type": "Reel",
      "date": "22 Jun",
      "link": "https://www.instagram.com/reel/DZ4U7mMiR3_/",
      "impressions": 3624,
      "engagement": 85,
      "likes": 68,
      "shares": 13,
      "saves": 3
     },
     {
      "msg": "Big news. Like really big",
      "network": "facebook",
      "type": "Post",
      "date": "1 Jun",
      "link": "https://facebook.com/1421660338130314_1446785280823601",
      "impressions": 3579,
      "engagement": 45,
      "likes": 36,
      "shares": 0,
      "saves": null
     },
     {
      "msg": "Looking for an off road couples van?",
      "network": "youtube",
      "type": "Video",
      "date": "23 Jun",
      "link": "https://www.youtube.com/watch?v=u9zoB9ZTuyc",
      "impressions": 2869,
      "engagement": 8,
      "likes": 6,
      "shares": null,
      "saves": null
     },
     {
      "msg": "This is the caravan the Christmas lights built",
      "network": "instagram",
      "type": "Reel",
      "date": "5 Jun",
      "link": "https://www.instagram.com/reel/DZMgl8qlWKk/",
      "impressions": 2309,
      "engagement": 44,
      "likes": 33,
      "shares": 4,
      "saves": 4
     }
    ],
    "tiktok_audience": {
     "impressions_sampled": 9659,
     "countries": [
      {
       "c": "Australia",
       "pct": 82.0
      },
      {
       "c": "United States",
       "pct": 7.0
      },
      {
       "c": "New Zealand",
       "pct": 2.9
      },
      {
       "c": "Other",
       "pct": 8.1
      }
     ],
     "gender": {
      "male": 58.9,
      "female": 41.1
     },
     "new_viewers_pct": 41.2,
     "non_follower_pct": 92.9
    }
   },
   "ob": {
    "channels": {
     "facebook": {
      "followers": 1140,
      "follower_change": 10,
      "impressions": 6201,
      "engagement": 65,
      "likes": 56,
      "comments": 6,
      "shares": 3,
      "profile_views": 0,
      "saves": 0,
      "messages": 7
     },
     "instagram": {
      "followers": 733,
      "follower_change": 80,
      "impressions": 88045,
      "engagement": 3240,
      "likes": 1428,
      "comments": 61,
      "shares": 731,
      "profile_views": 179,
      "saves": 285,
      "messages": 4
     }
    },
    "totals": {
     "followers": 1873,
     "follower_change": 90,
     "impressions": 94246,
     "engagement": 3305,
     "likes": 1484,
     "comments": 67,
     "shares": 734,
     "profile_views": 179,
     "saves": 285,
     "messages": 11,
     "engagement_rate": 3.51
    },
    "daily": {
     "dates": [
      "06/01",
      "06/02",
      "06/03",
      "06/04",
      "06/05",
      "06/06",
      "06/07",
      "06/08",
      "06/09",
      "06/10",
      "06/11",
      "06/12",
      "06/13",
      "06/14",
      "06/15",
      "06/16",
      "06/17",
      "06/18",
      "06/19",
      "06/20",
      "06/21",
      "06/22",
      "06/23",
      "06/24",
      "06/25",
      "06/26",
      "06/27",
      "06/28",
      "06/29",
      "06/30"
     ],
     "impressions": [
      1687,
      1365,
      421,
      321,
      1062,
      734,
      408,
      1559,
      443,
      1501,
      529,
      643,
      447,
      538,
      360,
      278,
      2888,
      1734,
      1916,
      1555,
      614,
      3623,
      2866,
      2191,
      950,
      1130,
      11807,
      39578,
      6441,
      4657
     ],
     "engagement": [
      65,
      34,
      9,
      7,
      21,
      9,
      4,
      45,
      16,
      43,
      14,
      3,
      4,
      5,
      7,
      3,
      98,
      46,
      50,
      14,
      15,
      94,
      77,
      50,
      29,
      20,
      500,
      1380,
      388,
      255
     ]
    },
    "top_posts": [
     {
      "msg": "Three kids, three beds, zero compromises",
      "network": "facebook",
      "type": "Reel",
      "date": "27 Jun",
      "link": "https://www.facebook.com/237207802819331_122231717900288079",
      "impressions": 1084,
      "engagement": 8,
      "likes": 8,
      "shares": 0,
      "saves": null
     },
     {
      "msg": "For couples chasing the open road",
      "network": "facebook",
      "type": "Reel",
      "date": "24 Jun",
      "link": "https://www.facebook.com/237207802819331_122231437754288079",
      "impressions": 744,
      "engagement": 7,
      "likes": 7,
      "shares": 0,
      "saves": null
     },
     {
      "msg": "Just the two of you, and the open road",
      "network": "facebook",
      "type": "Reel",
      "date": "22 Jun",
      "link": "https://www.facebook.com/237207802819331_122231254808288079",
      "impressions": 660,
      "engagement": 3,
      "likes": 3,
      "shares": 0,
      "saves": null
     },
     {
      "msg": "There's a switch in your caravan",
      "network": "facebook",
      "type": "Reel",
      "date": "26 Jun",
      "link": "https://www.facebook.com/237207802819331_122231620658288079",
      "impressions": 572,
      "engagement": 6,
      "likes": 6,
      "shares": 0,
      "saves": null
     }
    ]
   }
  },
  {
   "key": "2026-07",
   "label": "July 2026 (to 3 Jul)",
   "partial": true,
   "ac": {
    "new_contacts": 44,
    "ad_enquiries": 11,
    "deals_created": 11,
    "deals_by_type": {
     "Configurator": 5,
     "Ad enquiries": 3,
     "Sales-entered / other": 1,
     "Campaign offers": 1,
     "Brochure downloads": 1
    },
    "deals_by_state": {
     "NSW": 2,
     "VIC": 5,
     "QLD": 3,
     "WA": 1
    },
    "leads_by_state": {
     "NSW": 2,
     "VIC": 5,
     "QLD": 3,
     "WA": 1
    },
    "contacts_by_state": {
     "QLD": 5,
     "NSW": 4,
     "VIC": 3,
     "WA": 1,
     "NZ": 1,
     "TAS": 1,
     "No state recorded": 29
    },
    "brochures_by_model": {
     "XTR": 3,
     "Amaroo": 2,
     "Solara": 1
    },
    "configurator_leads": 5,
    "deposits_flow": {},
    "handovers_flow": {
     "VIC": 3
    },
    "deposits_names": [],
    "handovers_names": [
     "WL1209 David Campbell -  St",
     "WL1266 KIDSON",
     "WL1254 RANDALL HO2300RC"
    ],
    "emails": {
     "broadcast_count": 0,
     "sent": 0,
     "avg_open_pct": 0,
     "avg_click_pct": 0,
     "automated_sends": 6542,
     "broadcasts": []
    }
   },
   "wl": {
    "channels": {
     "youtube": {
      "followers": 738,
      "follower_change": 0,
      "impressions": 0,
      "engagement": 0,
      "likes": 0,
      "comments": 0,
      "shares": 0,
      "profile_views": 0,
      "saves": 0,
      "messages": 0
     },
     "linkedin": {
      "followers": 164,
      "follower_change": 0,
      "impressions": 53,
      "engagement": 1,
      "likes": 1,
      "comments": 0,
      "shares": 0,
      "profile_views": 0,
      "saves": 0,
      "messages": 0
     },
     "tiktok": {
      "followers": 507,
      "follower_change": 0,
      "impressions": 364,
      "engagement": 12,
      "likes": 9,
      "comments": 0,
      "shares": 3,
      "profile_views": 0,
      "saves": 0,
      "messages": 0
     },
     "facebook": {
      "followers": 24460,
      "follower_change": 0,
      "impressions": 36707,
      "engagement": 25,
      "likes": 23,
      "comments": 2,
      "shares": 0,
      "profile_views": 0,
      "saves": 0,
      "messages": 0
     },
     "instagram": {
      "followers": 9186,
      "follower_change": 26,
      "impressions": 84170,
      "engagement": 2680,
      "likes": 876,
      "comments": 18,
      "shares": 776,
      "profile_views": 680,
      "saves": 0,
      "messages": 0
     },
     "pinterest": {
      "followers": 18,
      "follower_change": 0,
      "impressions": 0,
      "engagement": 0,
      "likes": 0,
      "comments": 0,
      "shares": 0,
      "profile_views": 0,
      "saves": 0,
      "messages": 0
     }
    },
    "totals": {
     "followers": 35073,
     "follower_change": 26,
     "impressions": 121294,
     "engagement": 2718,
     "likes": 909,
     "comments": 20,
     "shares": 779,
     "profile_views": 680,
     "saves": 0,
     "messages": 0,
     "engagement_rate": 2.24
    },
    "daily": {
     "dates": [
      "07/01",
      "07/02",
      "07/03"
     ],
     "impressions": [
      40076,
      81218,
      0
     ],
     "engagement": [
      407,
      2310,
      1
     ]
    }
   },
   "ob": {
    "channels": {
     "facebook": {
      "followers": 1140,
      "follower_change": 0,
      "impressions": 349,
      "engagement": 6,
      "likes": 4,
      "comments": 2,
      "shares": 0,
      "profile_views": 0,
      "saves": 0,
      "messages": 0
     },
     "instagram": {
      "followers": 747,
      "follower_change": 6,
      "impressions": 30707,
      "engagement": 1224,
      "likes": 345,
      "comments": 12,
      "shares": 382,
      "profile_views": 47,
      "saves": 0,
      "messages": 0
     }
    },
    "totals": {
     "followers": 1887,
     "follower_change": 6,
     "impressions": 31056,
     "engagement": 1230,
     "likes": 349,
     "comments": 14,
     "shares": 382,
     "profile_views": 47,
     "saves": 0,
     "messages": 0,
     "engagement_rate": 3.96
    },
    "daily": {
     "dates": [
      "07/01",
      "07/02",
      "07/03"
     ],
     "impressions": [
      5190,
      25866,
      0
     ],
     "engagement": [
      240,
      990,
      0
     ]
    }
   }
  }
 ],
 "data_quality": {
  "mis_staged_money_stage": {
   "count": 13,
   "sample": [
    "Configurator:\u00a0Danielle Old",
    "Wl1178 -Rosehill lead",
    "Francesco & Candice Ienco",
    "Philip Andrew Clark",
    "B2ME TEST DEAL",
    "BARRY"
   ]
  },
  "configurator": {
   "deals_total": 224,
   "automation39_entries": 1504,
   "real_submissions_alltime_approx": 56,
   "no_name_deals": 41,
   "duplicate_deals": 45
  }
 }
}